Metadata-Version: 2.1
Name: swalot
Version: 0.0.3.post1
Summary: No CUDA out of memory again; fully use of a GPU card per user.
Home-page: https://github.com/cpfy/swalot
Author: cpfy
Author-email: 309301477@qq.com
License: MIT
Classifier: Programming Language :: Python :: 3
Classifier: License :: OSI Approved :: MIT License
Classifier: Operating System :: OS Independent
Requires-Python: >=3.6
License-File: LICENSE
Requires-Dist: numpy
Requires-Dist: GPUtil
Requires-Dist: rich
